fastload/__init__.py
fastload/downloader.py
fastload/fastload.py
fastload/progress_bar.py
fastload-0.0.3.dist-info/METADATA
fastload-0.0.3.dist-info/WHEEL
fastload-0.0.3.dist-info/top_level.txt
fastload-0.0.3.dist-info/RECORD
